{
  "pets": [
    {
      "nome": "Pipoca",
      "especie": "Cachorro",
      "raca": "Border Collie ",
      "idade": "5",
      "sexo": "Fêmea",
      "porte": "Grande",
      "peso": "19",
      "vacinado": "Sim",
      "vermifugado": "Sim",
      "castrado": "Sim",
      "condicao": "Nenhuma",
      "temperamento": "Dócil",
      "criancas": "Sim",
      "outrosPets": "Sim",
      "localizacao": "Rua Montanha Branca, 89",
      "id": "1"
    },
    {
      "nome": "Jade",
      "especie": "Cachorro",
      "raca": "Yorkshire",
      "idade": "10",
      "sexo": "Fêmea",
      "porte": "Pequeno",
      "peso": "5",
      "vacinado": "Sim",
      "vermifugado": "Sim",
      "castrado": "Sim",
      "condicao": "Cega",
      "temperamento": "Carente",
      "criancas": "Sim",
      "outrosPets": "Sim",
      "localizacao": "Rua Alameda, 23 ",
      "id": "2"
    },
    {
      "nome": "Thor",
      "especie": "Cachorro",
      "raca": "Labrador",
      "idade": "3",
      "sexo": "Macho",
      "porte": "Grande",
      "peso": "30",
      "vacinado": "Sim",
      "vermifugado": "Sim",
      "castrado": "Não",
      "condicao": "Nenhuma",
      "temperamento": "Brincalhão",
      "criancas": "Sim",
      "outrosPets": "Sim",
      "localizacao": "Rua das Palmeiras, 45",
      "id": "3"
    },
    {
      "nome": "Luna",
      "especie": "Gato",
      "raca": "Siamês",
      "idade": "2",
      "sexo": "Fêmea",
      "porte": "Pequeno",
      "peso": "4",
      "vacinado": "Sim",
      "vermifugado": "Sim",
      "castrado": "Sim",
      "condicao": "Nenhuma",
      "temperamento": "Curiosa",
      "criancas": "Sim",
      "outrosPets": "Não",
      "localizacao": "Av. Central, 100",
      "id": "4"
    },
    {
      "nome": "Max",
      "especie": "Cachorro",
      "raca": "Golden Retriever",
      "idade": "4",
      "sexo": "Macho",
      "porte": "Grande",
      "peso": "28",
      "vacinado": "Sim",
      "vermifugado": "Sim",
      "castrado": "Sim",
      "condicao": "Nenhuma",
      "temperamento": "Amigável",
      "criancas": "Sim",
      "outrosPets": "Sim",
      "localizacao": "Rua Flor do Campo, 300",
      "id": "5"
    },
    {
      "nome": "Mel",
      "especie": "Gato",
      "raca": "Persa",
      "idade": "6",
      "sexo": "Fêmea",
      "porte": "Pequeno",
      "peso": "3.5",
      "vacinado": "Sim",
      "vermifugado": "Sim",
      "castrado": "Sim",
      "condicao": "Doença renal",
      "temperamento": "Tranquila",
      "criancas": "Sim",
      "outrosPets": "Não",
      "localizacao": "Rua Ipê Roxo, 78",
      "id": "6"
    },
    {
      "nome": "Zeus",
      "especie": "Cachorro",
      "raca": "Pastor Alemão",
      "idade": "7",
      "sexo": "Macho",
      "porte": "Grande",
      "peso": "35",
      "vacinado": "Sim",
      "vermifugado": "Sim",
      "castrado": "Não",
      "condicao": "Nenhuma",
      "temperamento": "Protetor",
      "criancas": "Não",
      "outrosPets": "Não",
      "localizacao": "Rua do Cedro, 12",
      "id": "7"
    },
    {
      "nome": "Nina",
      "especie": "Cachorro",
      "raca": "Poodle",
      "idade": "9",
      "sexo": "Fêmea",
      "porte": "Pequeno",
      "peso": "6",
      "vacinado": "Sim",
      "vermifugado": "Sim",
      "castrado": "Sim",
      "condicao": "Artrose",
      "temperamento": "Calma",
      "criancas": "Sim",
      "outrosPets": "Sim",
      "localizacao": "Rua das Hortênsias, 5",
      "id": "8"
    },
    {
      "nome": "Apollo",
      "especie": "Cachorro",
      "raca": "Beagle",
      "idade": "2",
      "sexo": "Macho",
      "porte": "Médio",
      "peso": "12",
      "vacinado": "Sim",
      "vermifugado": "Sim",
      "castrado": "Não",
      "condicao": "Nenhuma",
      "temperamento": "Ativo",
      "criancas": "Sim",
      "outrosPets": "Sim",
      "localizacao": "Rua Sol Poente, 67",
      "id": "9"
    },
    {
      "nome": "Mimi",
      "especie": "Gato",
      "raca": "Mestiço",
      "idade": "1",
      "sexo": "Fêmea",
      "porte": "Pequeno",
      "peso": "2.8",
      "vacinado": "Sim",
      "vermifugado": "Sim",
      "castrado": "Sim",
      "condicao": "Nenhuma",
      "temperamento": "Brincalhona",
      "criancas": "Sim",
      "outrosPets": "Sim",
      "localizacao": "Rua Azul Marinho, 201",
      "id": "10"
    },
    {
      "nome": "Fred",
      "especie": "Cachorro",
      "raca": "Dachshund",
      "idade": "5",
      "sexo": "Macho",
      "porte": "Pequeno",
      "peso": "9",
      "vacinado": "Sim",
      "vermifugado": "Sim",
      "castrado": "Não",
      "condicao": "Sobrepeso",
      "temperamento": "Amável",
      "criancas": "Sim",
      "outrosPets": "Sim",
      "localizacao": "Rua do Girassol, 150",
      "id": "11"
    },
    {
      "nome": "Bela",
      "especie": "Gato",
      "raca": "Angorá",
      "idade": "3",
      "sexo": "Fêmea",
      "porte": "Pequeno",
      "peso": "3",
      "vacinado": "Sim",
      "vermifugado": "Sim",
      "castrado": "Sim",
      "condicao": "Nenhuma",
      "temperamento": "Afetuosa",
      "criancas": "Sim",
      "outrosPets": "Sim",
      "localizacao": "Rua do Luar, 88",
      "id": "12"
    }
  ]
}